dehumanizer/__init__.py
dehumanizer/dehumanizer.py
dehumanizer-0.0.2.dist-info/METADATA
dehumanizer-0.0.2.dist-info/WHEEL
dehumanizer-0.0.2.dist-info/top_level.txt
dehumanizer-0.0.2.dist-info/RECORD
