Metadata-Version: 2.1
Name: dehumanizer
Version: 0.0.2
Summary: Dehumanize number strings
Home-page: https://github.com/orlandodiaz/dehumanizer
Author: Orlando Diaz
Author-email: orlandodiaz.dev@gmail.com
License: UNKNOWN
Platform: UNKNOWN
Classifier: Programming Language :: Python :: 3
Classifier: License :: OSI Approved :: MIT License
Classifier: Operating System :: OS Independent
